saniti
