Metadata-Version: 2.1
Name: saniti
Version: 0.1.44
Summary: Sanitise text while keeping your sanity
Home-page: https://github.com/ChamRoshi/Saniti
Author: JBMountford
Author-email: jbm112358@gmail.com
License: UNKNOWN
Platform: UNKNOWN
Classifier: Programming Language :: Python :: 3
Classifier: License :: OSI Approved :: MIT License
Classifier: Operating System :: OS Independent
